d_flipflop/d_flipflop.v
module d_flipflop (
    input din,clk,
    output reg q
);
    always @(posedge clk) begin
        q <= din;
    end
endmodule

d_flipflop/d_flipflop_tb.v
`timescale 1ns/1ps

module d_flipflop_tb;

    // Declare signals
    reg din, clk;
    wire q;

    // Instantiate the D Flip-Flop (DUT)
    d_flipflop dut (
        .din(din),
        .clk(clk),
        .q(q)
    );

    // Clock generation: toggle every 5 ns => 10 ns period
    initial clk = 0;
    always #5 clk = ~clk;

    // Monitor output on every change
    initial begin
        $monitor("simulation_time = %0t | din = %b | clk = %b | q = %b", 
                  $time, din, clk, q);
    end

    // Test stimulus
    initial begin
        $dumpfile("d_flipflop.vcd");
        $dumpvars(0, d_flipflop_tb);

        // Apply stimulus
        din = 0; #10;
        din = 1; #10;
        din = 1; #10;
        din = 0; #10;
        din = 1; #10;

        $finish();
    end

endmodule

d_flipflop/d_flipflop.vcd
$date
	Tue Jul 08 16:48:04 2025
$end
$version
	Icarus Verilog
$end
$timescale
	1ps
$end
$scope module d_flipflop_tb $end
$var wire 1 ! q $end
$var reg 1 " clk $end
$var reg 1 # din $end
$scope module dut $end
$var wire 1 " clk $end
$var wire 1 # din $end
$var reg 1 ! q $end
$upscope $end
$upscope $end
$enddefinitions $end
$comment Show the parameter values. $end
$dumpall
$end
#0
$dumpvars
0#
0"
x!
$end
#5000
0!
1"
#10000
0"
1#
#15000
1!
1"
#20000
0"
#25000
1"
#30000
0"
0#
#35000
0!
1"
#40000
0"
1#
#45000
1!
1"
