register/register.v
module register #(parameter N = 4 ) (
    input [N-1:0] d, load,clear,clk,
    output reg [N-1:0] q
);
    
    always @(posedge clk or negedge clear) begin
        if(!clear)
        q <= {N{1'b0}};
        else if(load)
        q<=d;
    end


endmodule

register/register_tb.v
module register_tb ;
    parameter N=4;
  reg  [N-1:0] d, load,clear,clk;
  wire [N-1:0] q;


  register dut(.d(d),.load(load),.clear(clear),.clk(clk),.q(q));


  initial begin
    $monitor("simulation time is %0t, d = %b |  load =%d | clear=%d |   clk = %d |  q =%b",$time,d,load,clear,clk,q);
  end

initial
begin
    clk=0;
forever #5 clk=~clk;
end 

  initial begin

    $dumpfile("register.vcd");
     $dumpvars;

    d=4'b0000;     clear=1;    load=0; #10;  // initial values
    d=4'b0001;     clear=0;    load=1; #10; // clear = 0  reset the value 
   clear=1;    load=0; #10; //  clear =1 but the value does not update due to load 0
   clear=1;    load=1; #10;//  clear =1 but the value does  update due to load 1
    clear=0;    load=1; #10;  // clear = 0  reset the value 
$finish();

  end

endmodule

register/register.vcd
$date
	Wed Jul 09 15:20:01 2025
$end
$version
	Icarus Verilog
$end
$timescale
	1s
$end
$scope module register_tb $end
$var wire 4 ! q [3:0] $end
$var parameter 32 " N $end
$var reg 4 # clear [3:0] $end
$var reg 4 $ clk [3:0] $end
$var reg 4 % d [3:0] $end
$var reg 4 & load [3:0] $end
$scope module dut $end
$var wire 4 ' clear [3:0] $end
$var wire 4 ( clk [3:0] $end
$var wire 4 ) d [3:0] $end
$var wire 4 * load [3:0] $end
$var parameter 32 + N $end
$var reg 4 , q [3:0] $end
$upscope $end
$upscope $end
$enddefinitions $end
$comment Show the parameter values. $end
$dumpall
b100 +
b100 "
$end
#0
$dumpvars
bx ,
b0 *
b0 )
b0 (
b1 '
b0 &
b0 %
b0 $
b1 #
bx !
$end
#5
b1111 $
b1111 (
#10
b0 !
b0 ,
b0 $
b0 (
b1 &
b1 *
b0 #
b0 '
b1 %
b1 )
#15
b1111 $
b1111 (
#20
b0 $
b0 (
b0 &
b0 *
b1 #
b1 '
#25
b1111 $
b1111 (
#30
b0 $
b0 (
b1 &
b1 *
#35
b1 !
b1 ,
b1111 $
b1111 (
#40
b0 !
b0 ,
b0 $
b0 (
b0 #
b0 '
#45
b1111 $
b1111 (
#50
b0 $
b0 (
