mux_2x1/mux_2x1.v
module mux_2x1 (
    input [1:0]i,s,output reg y
);

always @(*) begin

case (s)
    1'b0: y=i[0];
    1'b1: y=i[1];
    default: y=1'bx;
endcase

end

    
endmodule

mux_2x1/mux_2x1_tb.v
`timescale 1ps/1ps

module mux_2x1_tb;

     reg [1:0]i,s;
     wire y;

    
 mux_2x1  dut(.i(i),.s(s),.y(y));

initial begin

 
     $dumpfile("mux_2x1.vcd"); // file name  of dut
    $dumpvars(0,mux_2x1_tb); // module name of test bench

             i=2'b00;s=1;
    #5 i=2'b01;s=1;
    #5 i=2'b10;s=1;
    #5 i=2'b11;s=1;
    #5 i=2'b00;s=0;
    #5 i=2'b01;s=0;
    #5 i=2'b10;s=0;
    #5 i=2'b11;s=0;

   
        #10 
    $finish();
end

initial begin
    $monitor("simulation_time =%g, i=%b,s=%0b,y=%b ",$time,i,s,y);
end


endmodule

// iverilog -o and_gate.vvp and_gate.v and_gate_tb.v   generate .vvp file then run vvp generated file   gtkwave and_gate.vcd   for waves

mux_2x1/mux_2x1.vcd
$date
	Mon Jul 07 11:58:22 2025
$end
$version
	Icarus Verilog
$end
$timescale
	1ps
$end
$scope module mux_2x1_tb $end
$var wire 1 ! y $end
$var reg 2 " i [1:0] $end
$var reg 2 # s [1:0] $end
$scope module dut $end
$var wire 2 $ i [1:0] $end
$var wire 2 % s [1:0] $end
$var reg 1 ! y $end
$upscope $end
$upscope $end
$enddefinitions $end
$comment Show the parameter values. $end
$dumpall
$end
#0
$dumpvars
b1 %
b0 $
b1 #
b0 "
0!
$end
#5
b1 "
b1 $
#10
1!
b10 "
b10 $
#15
b11 "
b11 $
#20
0!
b0 #
b0 %
b0 "
b0 $
#25
1!
b1 "
b1 $
#30
0!
b10 "
b10 $
#35
1!
b11 "
b11 $
