fsm_1/fsm_1.v
module fsm_1 (rst,clk,out);
    input wire rst;  //   active high reset
    input wire clk;  //  clock
    output reg out;  // output

    reg current_state;
    reg next_state;

    parameter s0 = 1'b0 ;
    parameter s1 = 1'b1;


// state transistion 
always @ (posedge clk   or  negedge rst  ) begin
 if (rst) begin
   current_state <= s0;
 end else begin
   current_state <= next_state;    
 end
end


// next state logic

always @(* ) begin
    case (current_state)
        s0:  next_state = s1;
        s1 : next_state = s0;
        default:  next_state = s0;
    endcase
end



// output logic

always @(*) begin
    case (current_state)
        s0: out = 1'b0; 
        s1: out = 1'b1; 
        default: out = 1'b0; 
    endcase
end


endmodule

fsm_1/fsm_1_tb.v
module fsm_1_tb;
    reg rst,clk;
    wire out;


// module  instance 
   fsm_1 dut(.rst(rst),.clk(clk),.out(out));


    initial begin
        clk=0;
        forever begin
            #5 clk = ~clk;
        end
    end

   initial begin
        $display("Time\tclk\trst\tout");
        $monitor("%0t\t%b\t%b\t%b", $time, clk, rst, out);

        rst = 1;       // Apply reset
        #12;
        rst = 0;       // Release reset

        #100;          // Run simulation for a while
        $finish;
    end


    initial begin
        $dumpfile("fsm_1.vcd");
        $dumpvars(0, fsm_1_tb);
    end


endmodule

fsm_1/fsm_1.vcd
$date
	Fri Jul 18 14:15:46 2025
$end
$version
	Icarus Verilog
$end
$timescale
	1s
$end
$scope module fsm_1_tb $end
$var wire 1 ! out $end
$var reg 1 " clk $end
$var reg 1 # rst $end
$scope module dut $end
$var wire 1 " clk $end
$var wire 1 # rst $end
$var parameter 1 $ s0 $end
$var parameter 1 % s1 $end
$var reg 1 & current_state $end
$var reg 1 ' next_state $end
$var reg 1 ! out $end
$upscope $end
$upscope $end
$enddefinitions $end
$comment Show the parameter values. $end
$dumpall
1%
0$
$end
#0
$dumpvars
x'
x&
1#
0"
x!
$end
#5
0!
1'
0&
1"
#10
0"
#12
0'
1!
1&
0#
#15
0!
1'
0&
1"
#20
0"
#25
0'
1!
1&
1"
#30
0"
#35
0!
1'
0&
1"
#40
0"
#45
0'
1!
1&
1"
#50
0"
#55
0!
1'
0&
1"
#60
0"
#65
0'
1!
1&
1"
#70
0"
#75
0!
1'
0&
1"
#80
0"
#85
0'
1!
1&
1"
#90
0"
#95
0!
1'
0&
1"
#100
0"
#105
0'
1!
1&
1"
